python_pqc_wrapping/__init__.py
python_pqc_wrapping/base.py
python_pqc_wrapping/common.py
python_pqc_wrapping/pqcwrappb/__init__.py
python_pqc_wrapping/pqcwrappb/blobwrap_pb2.py
python_pqc_wrapping/pqcwrappb/blobwrap_pb2.pyi
python_pqc_wrapping/pqcwrappb/wrap_pb2.py
python_pqc_wrapping/pqcwrappb/wrap_pb2.pyi
python_pqc_wrapping-0.0.15.dist-info/licenses/LICENSE
testing/__init__.py
testing/test_all.py
python_pqc_wrapping-0.0.15.dist-info/METADATA
python_pqc_wrapping-0.0.15.dist-info/WHEEL
python_pqc_wrapping-0.0.15.dist-info/top_level.txt
python_pqc_wrapping-0.0.15.dist-info/RECORD
