Metadata-Version: 2.4
Name: python_pqc_wrapping
Version: 0.0.15
Summary: AEAD encryption using Post Quantum Cryptography (ML-KEM)
Home-page: https://github.com/salrashid123/python_pqc_wrapping
Author: Sal Rashid
Author-email: salrashid123@gmail.com
Classifier: License :: OSI Approved :: Apache Software License
Classifier: Operating System :: OS Independent
Classifier: Development Status :: 3 - Alpha
Classifier: Intended Audience :: Developers
Classifier: Programming Language :: Python
Classifier: Programming Language :: Python :: 3.0
Classifier: Topic :: Software Development :: Libraries
Classifier: Topic :: Software Development :: Libraries :: Python Modules
License-File: LICENSE
Requires-Dist: pem
Requires-Dist: asn1tools
Requires-Dist: cryptography
Requires-Dist: protobuf
Requires-Dist: liboqs-python
Requires-Dist: google-cloud-kms
Provides-Extra: gcp
Requires-Dist: google-auth>=2.34.0; extra == "gcp"
Dynamic: author
Dynamic: author-email
Dynamic: classifier
Dynamic: description
Dynamic: description-content-type
Dynamic: home-page
Dynamic: license-file
Dynamic: provides-extra
Dynamic: requires-dist
Dynamic: summary
